clovers_utils/library.py
clovers_utils/tools.py
clovers_utils/linecard/__init__.py
clovers_utils/linecard/linecard_parsing.cpython-313-i386-linux-gnu.so
clovers_utils/linecard/linecard_parsing.pyi
clovers_utils-0.2.4.dist-info/METADATA
clovers_utils-0.2.4.dist-info/WHEEL
clovers_utils-0.2.4.dist-info/top_level.txt
clovers_utils-0.2.4.dist-info/RECORD
clovers_utils-0.2.4.dist-info/licenses/LICENSE
